Metadata-Version: 2.1
Name: pminsight
Version: 0.0.1
Summary: Tools for Product manager
Home-page: https://github.com/AlexTengT/pminsight
Author: Alex Teng
Author-email: 
License: MIT License
Keywords: pip,pm,pmInsight
Platform: any
License-File: LICENSE
